scrapy_feedexporter_sftp/__init__.py
scrapy_feedexporter_sftp-1.1.0.dist-info/LICENSE
scrapy_feedexporter_sftp-1.1.0.dist-info/METADATA
scrapy_feedexporter_sftp-1.1.0.dist-info/WHEEL
scrapy_feedexporter_sftp-1.1.0.dist-info/top_level.txt
scrapy_feedexporter_sftp-1.1.0.dist-info/RECORD
